simplehook/SimpleHook.py
simplehook/SimpleHookAsync.py
simplehook/__init__.py
simplehook-1.4.4.dist-info/LICENSE
simplehook-1.4.4.dist-info/LICENSES.txt
simplehook-1.4.4.dist-info/METADATA
simplehook-1.4.4.dist-info/WHEEL
simplehook-1.4.4.dist-info/top_level.txt
simplehook-1.4.4.dist-info/RECORD
