Metadata-Version: 2.1
Name: simplehook
Version: 1.4.4
Summary: Simple Discord webhook wrapper
Home-page: https://github.com/jstiin/simplehook
Author: jstiin
License: AGPL-3.0-only
Keywords: discord webhook messaging
Classifier: Programming Language :: Python :: 3
Classifier: License :: OSI Approved :: GNU Affero General Public License v3
Requires-Python: >=3.7
License-File: LICENSE
License-File: LICENSES.txt
Requires-Dist: aiofiles
Requires-Dist: httpx
Provides-Extra: dev
Requires-Dist: pytest; extra == "dev"
Requires-Dist: pytest-cov; extra == "dev"
Requires-Dist: pytest-async; extra == "dev"
